pykabutan/__init__.py
pykabutan/_scraper.py
pykabutan/config.py
pykabutan/exceptions.py
pykabutan/profile.py
pykabutan/search.py
pykabutan/ticker.py
pykabutan-0.1.1.dist-info/METADATA
pykabutan-0.1.1.dist-info/WHEEL
pykabutan-0.1.1.dist-info/RECORD
