Metadata-Version: 2.4
Name: pykabutan
Version: 0.1.1
Summary: A clean, beginner-friendly Python library for scraping kabutan.jp
Author-email: obichan117 <obichan117@gmail.com>
License: MIT
Keywords: finance,japan,kabutan,scraping,stock
Classifier: Development Status :: 3 - Alpha
Classifier: Intended Audience :: Developers
Classifier: License :: OSI Approved :: MIT License
Classifier: Programming Language :: Python :: 3
Classifier: Programming Language :: Python :: 3.10
Classifier: Programming Language :: Python :: 3.11
Classifier: Programming Language :: Python :: 3.12
Classifier: Topic :: Office/Business :: Financial :: Investment
Requires-Python: >=3.10
Requires-Dist: beautifulsoup4>=4.12
Requires-Dist: lxml>=5.0
Requires-Dist: pandas>=2.0
Requires-Dist: requests>=2.32
Provides-Extra: dev
Requires-Dist: mypy>=1.13; extra == 'dev'
Requires-Dist: pytest-mock>=3.14; extra == 'dev'
Requires-Dist: pytest>=8.0; extra == 'dev'
Requires-Dist: ruff>=0.8; extra == 'dev'
